noerr.py
noerr-1.0.0a0.dist-info/LICENSE
noerr-1.0.0a0.dist-info/WHEEL
noerr-1.0.0a0.dist-info/METADATA
noerr-1.0.0a0.dist-info/RECORD
