Metadata-Version: 2.1
Name: noerr
Version: 1.0.0a0
Summary: Catch exceptions via a context manager in Python
Author: Chris Griffith
Author-email: chris@cdgriffith.com
Requires-Python: >=3.6,<4.0
Classifier: Programming Language :: Python :: 3
Classifier: Programming Language :: Python :: 3.6
Classifier: Programming Language :: Python :: 3.7
Classifier: Programming Language :: Python :: 3.8
